[
    {
        "program": "Accounting, B.S. (Abington)",
        "campuses": [
            "Abington"
        ]
    },
    {
        "program": "Accounting, B.S. (Altoona)",
        "campuses": [
            "Altoona"
        ]
    },
    {
        "program": "Accounting, B.S. (Behrend)",
        "campuses": [
            "Erie"
        ]
    },
    {
        "program": "Accounting, B.S. (Berks)",
        "campuses": [
            "Berks"
        ]
    },
    {
        "program": "Accounting, B.S. (Business)",
        "campuses": [
            "University Park"
        ]
    },
    {
        "program": "Accounting, B.S. (Capital)",
        "campuses": [
            "Harrisburg",
            "World Campus"
        ]
    },
    {
        "program": "Acting, B.F.A.",
        "campuses": [
            "University Park"
        ]
    },
    {
        "program": "Actuarial Science, B.S.",
        "campuses": [
            "University Park"
        ]
    },
    {
        "program": "Administration of Justice, B.A.",
        "campuses": [
            "DuBois",
            "Fayette",
            "Greater Allegheny",
            "Hazleton",
            "Schuylkill",
            "Wilkes-Barre"
        ]
    },
    {
        "program": "Administration of Justice, B.S.",
        "campuses": [
            "Beaver",
            "DuBois",
            "Fayette",
            "Greater Allegheny",
            "Hazleton",
            "New Kensington",
            "Schuylkill",
            "Shenango",
            "Wilkes-Barre"
        ]
    },
    {
        "program": "Advertising/Public Relations, B.A.",
        "campuses": [
            "University Park"
        ]
    },
    {
        "program": "Aerospace Engineering, B.S.",
        "campuses": [
            "University Park"
        ]
    },
    {
        "program": "African American Studies, B.A.",
        "campuses": [
            "University Park"
        ]
    },
    {
        "program": "African and African American Studies, B.A.",
        "campuses": [
            "University Park"
        ]
    },
    {
        "program": "African and African American Studies, B.S.",
        "campuses": [
            "University Park"
        ]
    },
    {
        "program": "African Studies, B.A.",
        "campuses": [
            "University Park"
        ]
    },
    {
        "program": "Agribusiness Management, B.S.",
        "campuses": [
            "University Park",
            "World Campus"
        ]
    },
    {
        "program": "Agricultural and Biorenewable Systems Management, B.S.",
        "campuses": [
            "University Park"
        ]
    },
    {
        "program": "Agricultural and Extension Education, B.S.",
        "campuses": [
            "University Park"
        ]
    },
    {
        "program": "Agricultural Science, B.S.",
        "campuses": [
            "University Park"
        ]
    },
    {
        "program": "Air Force ROTC",
        "campuses": []
    },
    {
        "program": "American Studies, B.A. (Abington)",
        "campuses": [
            "Abington"
        ]
    },
    {
        "program": "American Studies, B.A. (Capital)",
        "campuses": [
            "Harrisburg"
        ]
    },
    {
        "program": "American Studies, B.A. (University College)",
        "campuses": [
            "Brandywine"
        ]
    },
    {
        "program": "Animal Science, B.S.",
        "campuses": [
            "University Park"
        ]
    },
    {
        "program": "Anthropological Science, B.S.",
        "campuses": [
            "University Park"
        ]
    },
    {
        "program": "Anthropology, B.A.",
        "campuses": [
            "University Park"
        ]
    },
    {
        "program": "Applied Linguistics, B.A.",
        "campuses": [
            "University Park"
        ]
    },
    {
        "program": "Architectural Engineering, B.A.E.",
        "campuses": [
            "University Park"
        ]
    },
    {
        "program": "Architecture, B.Arch.",
        "campuses": [
            "University Park"
        ]
    },
    {
        "program": "Architecture, B.S.",
        "campuses": [
            "University Park"
        ]
    },
    {
        "program": "Army ROTC",
        "campuses": []
    },
    {
        "program": "Art Education, B.S.",
        "campuses": [
            "University Park"
        ]
    },
    {
        "program": "Art History, B.A.",
        "campuses": [
            "University Park"
        ]
    },
    {
        "program": "Art, B.A. (Abington)",
        "campuses": [
            "Abington"
        ]
    },
    {
        "program": "Art, B.A. (Arts and Architecture)",
        "campuses": [
            "University Park"
        ]
    },
    {
        "program": "Art, B.F.A.",
        "campuses": [
            "University Park"
        ]
    },
    {
        "program": "Artificial Intelligence Engineering, B.S.",
        "campuses": [
            "University Park"
        ]
    },
    {
        "program": "Artificial Intelligence Methods and Applications, B.S. (Capital)",
        "campuses": [
            "Harrisburg"
        ]
    },
    {
        "program": "Artificial Intelligence Methods and Applications, B.S. (Information Sciences and Technology)",
        "campuses": [
            "University Park"
        ]
    },
    {
        "program": "Arts Administration, B.A.",
        "campuses": [
            "Lehigh Valley"
        ]
    },
    {
        "program": "Asian Studies, B.A.",
        "campuses": [
            "University Park"
        ]
    },
    {
        "program": "Astronomy and Astrophysics, B.S.",
        "campuses": [
            "University Park"
        ]
    },
    {
        "program": "Bachelor of Philosophy Degree",
        "campuses": [
            "University Park"
        ]
    },
    {
        "program": "Biobehavioral Health, B.S. (Behrend)",
        "campuses": [
            "Erie"
        ]
    },
    {
        "program": "Biobehavioral Health, B.S. (Capital)",
        "campuses": [
            "Harrisburg"
        ]
    },
    {
        "program": "Biobehavioral Health, B.S. (Health and Human Development)",
        "campuses": [
            "University Park",
            "World Campus"
        ]
    },
    {
        "program": "Biobehavioral Health, B.S. (University College)",
        "campuses": [
            "Greater Allegheny",
            "Lehigh Valley",
            "New Kensington"
        ]
    },
    {
        "program": "Biochemistry and Molecular Biology, B.S. (Berks)",
        "campuses": [
            "Berks"
        ]
    },
    {
        "program": "Biochemistry and Molecular Biology, B.S. (Science)",
        "campuses": [
            "University Park"
        ]
    },
    {
        "program": "Biological Engineering, B.S.",
        "campuses": [
            "University Park"
        ]
    },
    {
        "program": "Biology, B.S. (Abington)",
        "campuses": [
            "Abington"
        ]
    },
    {
        "program": "Biology, B.S. (Altoona)",
        "campuses": [
            "Altoona"
        ]
    },
    {
        "program": "Biology, B.S. (Behrend)",
        "campuses": [
            "Erie"
        ]
    },
    {
        "program": "Biology, B.S. (Berks)",
        "campuses": [
            "Berks"
        ]
    },
    {
        "program": "Biology, B.S. (Capital)",
        "campuses": [
            "Harrisburg"
        ]
    },
    {
        "program": "Biology, B.S. (Science)",
        "campuses": [
            "University Park"
        ]
    },
    {
        "program": "Biology, B.S. (University College)",
        "campuses": [
            "Beaver",
            "Brandywine",
            "Lehigh Valley",
            "Schuylkill",
            "Scranton",
            "York"
        ]
    },
    {
        "program": "Biomedical Engineering, B.S.",
        "campuses": [
            "University Park"
        ]
    },
    {
        "program": "Biotechnology, B.S.",
        "campuses": [
            "University Park"
        ]
    },
    {
        "program": "Business Analytics and Information Systems, B.S.",
        "campuses": [
            "University Park"
        ]
    },
    {
        "program": "Business Economics, B.S.",
        "campuses": [
            "Erie"
        ]
    },
    {
        "program": "Business, B.S. (Abington)",
        "campuses": [
            "Abington"
        ]
    },
    {
        "program": "Business, B.S. (Altoona)",
        "campuses": [
            "Altoona"
        ]
    },
    {
        "program": "Business, B.S. (Berks)",
        "campuses": [
            "Berks"
        ]
    },
    {
        "program": "Business, B.S. (Intercollege)",
        "campuses": [
            "World Campus"
        ]
    },
    {
        "program": "Business, B.S. (University College)",
        "campuses": [
            "Beaver",
            "Brandywine",
            "DuBois",
            "Fayette",
            "Greater Allegheny",
            "Hazleton",
            "Lehigh Valley",
            "Mont Alto",
            "New Kensington",
            "Schuylkill",
            "Scranton",
            "Shenango",
            "Wilkes-Barre",
            "York"
        ]
    },
    {
        "program": "Chemical Engineering, B.S.",
        "campuses": [
            "University Park"
        ]
    },
    {
        "program": "Chemistry, B.S. (Behrend)",
        "campuses": [
            "Erie"
        ]
    },
    {
        "program": "Chemistry, B.S. (Science)",
        "campuses": [
            "University Park"
        ]
    },
    {
        "program": "Chinese, B.A.",
        "campuses": [
            "University Park"
        ]
    },
    {
        "program": "Civil Engineering, B.S. (Capital)",
        "campuses": [
            "Harrisburg"
        ]
    },
    {
        "program": "Civil Engineering, B.S. (Engineering)",
        "campuses": [
            "University Park"
        ]
    },
    {
        "program": "Classics and Ancient Mediterranean Studies, B.A.",
        "campuses": [
            "University Park"
        ]
    },
    {
        "program": "Communication Arts and Sciences, B.A. (Berks)",
        "campuses": [
            "Berks"
        ]
    },
    {
        "program": "Communication Arts and Sciences, B.A. (Liberal Arts)",
        "campuses": [
            "University Park"
        ]
    },
    {
        "program": "Communication Arts and Sciences, B.A. (University College)",
        "campuses": [
            "Brandywine"
        ]
    },
    {
        "program": "Communication Arts and Sciences, B.S.",
        "campuses": [
            "University Park"
        ]
    },
    {
        "program": "Communication Sciences and Disorders, B.S. (Capital)",
        "campuses": [
            "Harrisburg"
        ]
    },
    {
        "program": "Communication Sciences and Disorders, B.S. (Health and Human Development)",
        "campuses": [
            "University Park"
        ]
    },
    {
        "program": "Communications, B.A (Altoona)",
        "campuses": [
            "Altoona"
        ]
    },
    {
        "program": "Communications, B.A. (Capital)",
        "campuses": [
            "Harrisburg"
        ]
    },
    {
        "program": "Communications, B.A. (University College)",
        "campuses": [
            "Brandywine",
            "Lehigh Valley",
            "New Kensington"
        ]
    },
    {
        "program": "Community, Environment, and Development, B.S.",
        "campuses": [
            "University Park"
        ]
    },
    {
        "program": "Comparative Literature, B.A.",
        "campuses": [
            "University Park"
        ]
    },
    {
        "program": "Computer Engineering, B.S. (Behrend)",
        "campuses": [
            "Erie"
        ]
    },
    {
        "program": "Computer Engineering, B.S. (Engineering)",
        "campuses": [
            "University Park"
        ]
    },
    {
        "program": "Computer Science, B.S. (Abington)",
        "campuses": [
            "Abington"
        ]
    },
    {
        "program": "Computer Science, B.S. (Behrend)",
        "campuses": [
            "Erie"
        ]
    },
    {
        "program": "Computer Science, B.S. (Capital)",
        "campuses": [
            "Harrisburg"
        ]
    },
    {
        "program": "Computer Science, B.S. (Engineering)",
        "campuses": [
            "Beaver",
            "Brandywine",
            "Hazleton",
            "University Park"
        ]
    },
    {
        "program": "Corporate Communication, B.A. (Abington)",
        "campuses": [
            "Abington"
        ]
    },
    {
        "program": "Corporate Communication, B.A. (University College)",
        "campuses": [
            "Fayette",
            "Hazleton",
            "Schuylkill",
            "Scranton",
            "Wilkes-Barre",
            "York"
        ]
    },
    {
        "program": "Corporate Innovation and Entrepreneurship, B.S.",
        "campuses": [
            "University Park"
        ]
    },
    {
        "program": "Creative Writing, B.F.A.",
        "campuses": [
            "Erie"
        ]
    },
    {
        "program": "Criminal Justice, B.A. (Abington)",
        "campuses": [
            "Abington"
        ]
    },
    {
        "program": "Criminal Justice, B.A. (Altoona)",
        "campuses": [
            "Altoona"
        ]
    },
    {
        "program": "Criminal Justice, B.A. (Berks)",
        "campuses": [
            "Berks"
        ]
    },
    {
        "program": "Criminal Justice, B.A. (University College)",
        "campuses": [
            "Beaver",
            "DuBois",
            "Fayette",
            "Greater Allegheny",
            "Hazleton",
            "Lehigh Valley",
            "New Kensington",
            "Schuylkill",
            "Shenango",
            "Wilkes-Barre"
        ]
    },
    {
        "program": "Criminal Justice, B.S. (Abington)",
        "campuses": [
            "Abington"
        ]
    },
    {
        "program": "Criminal Justice, B.S. (Altoona)",
        "campuses": [
            "Altoona"
        ]
    },
    {
        "program": "Criminal Justice, B.S. (Berks)",
        "campuses": [
            "Berks"
        ]
    },
    {
        "program": "Criminal Justice, B.S. (Capital)",
        "campuses": [
            "Harrisburg",
            "World Campus"
        ]
    },
    {
        "program": "Criminal Justice, B.S. (University College)",
        "campuses": [
            "Beaver",
            "DuBois",
            "Fayette",
            "Greater Allegheny",
            "Hazleton",
            "Lehigh Valley",
            "New Kensington",
            "Schuylkill",
            "Shenango",
            "Wilkes-Barre"
        ]
    },
    {
        "program": "Criminology, B.A.",
        "campuses": [
            "University Park"
        ]
    },
    {
        "program": "Criminology, B.S.",
        "campuses": [
            "University Park"
        ]
    },
    {
        "program": "Cybersecurity Analytics and Operations, B.S. (Abington)",
        "campuses": [
            "Abington"
        ]
    },
    {
        "program": "Cybersecurity Analytics and Operations, B.S. (Altoona)",
        "campuses": [
            "Altoona"
        ]
    },
    {
        "program": "Cybersecurity Analytics and Operations, B.S. (Berks)",
        "campuses": [
            "Berks"
        ]
    },
    {
        "program": "Cybersecurity Analytics and Operations, B.S. (Capital)",
        "campuses": [
            "Harrisburg"
        ]
    },
    {
        "program": "Cybersecurity Analytics and Operations, B.S. (Information Sciences and Technology)",
        "campuses": [
            "University Park",
            "World Campus"
        ]
    },
    {
        "program": "Cybersecurity Analytics and Operations, B.S. (University College)",
        "campuses": [
            "Beaver",
            "Brandywine",
            "Greater Allegheny",
            "Lehigh Valley",
            "Schuylkill",
            "York"
        ]
    },
    {
        "program": "Data Sciences, B.S. (Abington)",
        "campuses": [
            "Abington"
        ]
    },
    {
        "program": "Data Sciences, B.S. (Engineering)",
        "campuses": [
            "University Park"
        ]
    },
    {
        "program": "Data Sciences, B.S. (Information Sciences and Technology)",
        "campuses": [
            "University Park"
        ]
    },
    {
        "program": "Data Sciences, B.S. (Science)",
        "campuses": [
            "University Park"
        ]
    },
    {
        "program": "Digital Arts and Media Design, B.Des.",
        "campuses": [
            "University Park"
        ]
    },
    {
        "program": "Digital Journalism and Media, B.A.",
        "campuses": [
            "World Campus"
        ]
    },
    {
        "program": "Digital Media, Arts, and Technology, B.A.",
        "campuses": [
            "Erie"
        ]
    },
    {
        "program": "Digital Multimedia Design, B.Des.",
        "campuses": [
            "World Campus"
        ]
    },
    {
        "program": "Earth Science and Policy, B.S.",
        "campuses": [
            "University Park"
        ]
    },
    {
        "program": "Earth Sciences, B.S.",
        "campuses": [
            "University Park"
        ]
    },
    {
        "program": "Economics, B.A. (Behrend)",
        "campuses": [
            "Erie"
        ]
    },
    {
        "program": "Economics, B.A. (Liberal Arts)",
        "campuses": [
            "University Park",
            "World Campus"
        ]
    },
    {
        "program": "Economics, B.S.",
        "campuses": [
            "University Park",
            "World Campus"
        ]
    },
    {
        "program": "Education and Public Policy, B.S.",
        "campuses": [
            "University Park"
        ]
    },
    {
        "program": "Electrical and Computer Engineering Technology, B.S.",
        "campuses": [
            "Erie"
        ]
    },
    {
        "program": "Electrical Engineering Technology, B.S. (Capital)",
        "campuses": [
            "Harrisburg"
        ]
    },
    {
        "program": "Electrical Engineering Technology, B.S. (Engineering)",
        "campuses": [
            "Wilkes-Barre"
        ]
    },
    {
        "program": "Electrical Engineering, B.S. (Behrend)",
        "campuses": [
            "Erie"
        ]
    },
    {
        "program": "Electrical Engineering, B.S. (Capital)",
        "campuses": [
            "Harrisburg"
        ]
    },
    {
        "program": "Electrical Engineering, B.S. (Engineering)",
        "campuses": [
            "University Park"
        ]
    },
    {
        "program": "Electro-Mechanical Engineering Technology, B.S. (Altoona)",
        "campuses": [
            "Altoona"
        ]
    },
    {
        "program": "Electro-Mechanical Engineering Technology, B.S. (Berks)",
        "campuses": [
            "Berks"
        ]
    },
    {
        "program": "Electro-Mechanical Engineering Technology, B.S. (Engineering)",
        "campuses": [
            "Fayette",
            "New Kensington",
            "York"
        ]
    },
    {
        "program": "Elementary and Early Childhood Education, B.S.",
        "campuses": [
            "Abington",
            "Altoona",
            "Berks",
            "Erie",
            "University Park"
        ]
    },
    {
        "program": "Elementary and Kindergarten Education, B.S. (Altoona)",
        "campuses": [
            "Altoona"
        ]
    },
    {
        "program": "Elementary and Kindergarten Education, B.S. (Berks)",
        "campuses": [
            "Berks"
        ]
    },
    {
        "program": "Elementary and Kindergarten Education, B.S. (Education)",
        "campuses": [
            "University Park"
        ]
    },
    {
        "program": "Elementary Education, B.El.Ed.",
        "campuses": [
            "Harrisburg"
        ]
    },
    {
        "program": "Energy and Sustainability Policy, B.A.",
        "campuses": [
            "World Campus"
        ]
    },
    {
        "program": "Energy and Sustainability Policy, B.S.",
        "campuses": [
            "World Campus"
        ]
    },
    {
        "program": "Energy Business and Finance, B.S.",
        "campuses": [
            "University Park"
        ]
    },
    {
        "program": "Energy Engineering, B.S.",
        "campuses": [
            "University Park"
        ]
    },
    {
        "program": "Engineering Science, B.S.",
        "campuses": [
            "University Park"
        ]
    },
    {
        "program": "Engineering, B.S.",
        "campuses": [
            "Abington",
            "Brandywine",
            "DuBois",
            "Hazleton",
            "Lehigh Valley"
        ]
    },
    {
        "program": "English, B.A. (Abington)",
        "campuses": [
            "Abington"
        ]
    },
    {
        "program": "English, B.A. (Altoona)",
        "campuses": [
            "Altoona"
        ]
    },
    {
        "program": "English, B.A. (Behrend)",
        "campuses": [
            "Erie"
        ]
    },
    {
        "program": "English, B.A. (Liberal Arts)",
        "campuses": [
            "University Park"
        ]
    },
    {
        "program": "English, B.A. (University College)",
        "campuses": [
            "Brandywine",
            "Scranton",
            "York"
        ]
    },
    {
        "program": "English, B.Hum.",
        "campuses": [
            "Harrisburg"
        ]
    },
    {
        "program": "Enterprise Technology Integration, B.S. (Capital)",
        "campuses": [
            "Harrisburg"
        ]
    },
    {
        "program": "Enterprise Technology Integration, B.S. (Information Sciences and Technology)",
        "campuses": [
            "University Park",
            "World Campus"
        ]
    },
    {
        "program": "Environmental Resource Management, B.S.",
        "campuses": [
            "University Park"
        ]
    },
    {
        "program": "Environmental Science, B.S.",
        "campuses": [
            "Erie"
        ]
    },
    {
        "program": "Environmental Studies, B.A.",
        "campuses": [
            "Altoona"
        ]
    },
    {
        "program": "Environmental Studies, B.S.",
        "campuses": [
            "Altoona"
        ]
    },
    {
        "program": "Environmental Systems Engineering, B.S.",
        "campuses": [
            "University Park"
        ]
    },
    {
        "program": "Film Production, B.A.",
        "campuses": [
            "University Park"
        ]
    },
    {
        "program": "Finance, B.S. (Abington)",
        "campuses": [
            "Abington"
        ]
    },
    {
        "program": "Finance, B.S. (Behrend)",
        "campuses": [
            "Erie",
            "World Campus"
        ]
    },
    {
        "program": "Finance, B.S. (Business)",
        "campuses": [
            "University Park"
        ]
    },
    {
        "program": "Finance, B.S. (Capital)",
        "campuses": [
            "Harrisburg"
        ]
    },
    {
        "program": "Food Science, B.S.",
        "campuses": [
            "University Park"
        ]
    },
    {
        "program": "Forensic Science, B.S.",
        "campuses": [
            "University Park"
        ]
    },
    {
        "program": "Forest Ecosystems, B.S.",
        "campuses": [
            "University Park"
        ]
    },
    {
        "program": "French and Francophone Studies, B.A.",
        "campuses": [
            "University Park"
        ]
    },
    {
        "program": "French and Francophone Studies, B.S.",
        "campuses": [
            "University Park"
        ]
    },
    {
        "program": "Functional Data Analytics, B.S.",
        "campuses": [
            "Erie",
            "World Campus"
        ]
    },
    {
        "program": "Geobiology, B.S.",
        "campuses": [
            "University Park"
        ]
    },
    {
        "program": "Geography, B.A.",
        "campuses": [
            "University Park"
        ]
    },
    {
        "program": "Geography, B.S.",
        "campuses": [
            "University Park"
        ]
    },
    {
        "program": "Geosciences, B.A.",
        "campuses": [
            "University Park"
        ]
    },
    {
        "program": "Geosciences, B.S.",
        "campuses": [
            "University Park"
        ]
    },
    {
        "program": "German, B.A.",
        "campuses": [
            "University Park"
        ]
    },
    {
        "program": "German, B.S.",
        "campuses": [
            "University Park"
        ]
    },
    {
        "program": "Global and International Studies Major",
        "campuses": [
            "University Park"
        ]
    },
    {
        "program": "Global and International Studies, B.A.",
        "campuses": [
            "University Park"
        ]
    },
    {
        "program": "Global and International Studies, B.S.",
        "campuses": [
            "University Park"
        ]
    },
    {
        "program": "Global Studies, B.A.",
        "campuses": [
            "Berks"
        ]
    },
    {
        "program": "Graphic Design, B.Des.",
        "campuses": [
            "University Park"
        ]
    },
    {
        "program": "Health Humanities, B.A.",
        "campuses": [
            "Abington"
        ]
    },
    {
        "program": "Health Humanities, B.S.",
        "campuses": [
            "Abington"
        ]
    },
    {
        "program": "Health Policy and Administration, B.S. (Capital)",
        "campuses": [
            "Harrisburg"
        ]
    },
    {
        "program": "Health Policy and Administration, B.S. (Health and Human Development)",
        "campuses": [
            "University Park",
            "World Campus"
        ]
    },
    {
        "program": "Health Policy and Administration, B.S. (University College)",
        "campuses": [
            "Beaver",
            "Hazleton",
            "Lehigh Valley",
            "Mont Alto",
            "Shenango"
        ]
    },
    {
        "program": "History, B.A. (Abington)",
        "campuses": [
            "Abington"
        ]
    },
    {
        "program": "History, B.A. (Altoona)",
        "campuses": [
            "Altoona"
        ]
    },
    {
        "program": "History, B.A. (Behrend)",
        "campuses": [
            "Erie"
        ]
    },
    {
        "program": "History, B.A. (Liberal Arts)",
        "campuses": [
            "University Park",
            "World Campus"
        ]
    },
    {
        "program": "Hospitality Management, B.S. (Berks)",
        "campuses": [
            "Berks"
        ]
    },
    {
        "program": "Hospitality Management, B.S. (Health and Human Development)",
        "campuses": [
            "University Park"
        ]
    },
    {
        "program": "Human Capital Management, B.S.",
        "campuses": [
            "Harrisburg"
        ]
    },
    {
        "program": "Human Development and Family Studies, B.S. (Altoona)",
        "campuses": [
            "Altoona"
        ]
    },
    {
        "program": "Human Development and Family Studies, B.S. (Capital)",
        "campuses": [
            "Harrisburg"
        ]
    },
    {
        "program": "Human Development and Family Studies, B.S. (Health and Human Development)",
        "campuses": [
            "University Park",
            "World Campus"
        ]
    },
    {
        "program": "Human Development and Family Studies, B.S. (University College)",
        "campuses": [
            "Brandywine",
            "DuBois",
            "Fayette",
            "Mont Alto",
            "Scranton",
            "Shenango",
            "York"
        ]
    },
    {
        "program": "Human-Centered Design and Development, B.S. (Capital)",
        "campuses": [
            "Harrisburg"
        ]
    },
    {
        "program": "Human-Centered Design and Development, B.S. (Information Sciences and Technology)",
        "campuses": [
            "University Park"
        ]
    },
    {
        "program": "Humanities, B.A. (Capital)",
        "campuses": [
            "Harrisburg"
        ]
    },
    {
        "program": "Humanities, B.A. (University College)",
        "campuses": [
            "Fayette"
        ]
    },
    {
        "program": "Immunology and Infectious Disease, B.S.",
        "campuses": [
            "University Park"
        ]
    },
    {
        "program": "Industrial Engineering, B.S. (Behrend)",
        "campuses": [
            "Erie"
        ]
    },
    {
        "program": "Industrial Engineering, B.S. (Engineering)",
        "campuses": [
            "University Park"
        ]
    },
    {
        "program": "Information Sciences and Technology, B.S. (Capital)",
        "campuses": [
            "Harrisburg"
        ]
    },
    {
        "program": "Information Sciences and Technology, B.S. (Information Sciences and Technology)",
        "campuses": [
            "World Campus"
        ]
    },
    {
        "program": "Information Systems, B.S.",
        "campuses": [
            "Harrisburg"
        ]
    },
    {
        "program": "Information Technology Ethics and Compliance, B.S.",
        "campuses": [
            "University Park"
        ]
    },
    {
        "program": "Information Technology, B.S. (Abington)",
        "campuses": [
            "Abington"
        ]
    },
    {
        "program": "Information Technology, B.S. (Altoona)",
        "campuses": [
            "Altoona"
        ]
    },
    {
        "program": "Information Technology, B.S. (Berks)",
        "campuses": [
            "Berks"
        ]
    },
    {
        "program": "Information Technology, B.S. (University College)",
        "campuses": [
            "Beaver",
            "Brandywine",
            "DuBois",
            "Greater Allegheny",
            "Hazleton",
            "Lehigh Valley",
            "Mont Alto",
            "New Kensington",
            "Schuylkill",
            "Scranton",
            "Shenango",
            "Wilkes-Barre",
            "York"
        ]
    },
    {
        "program": "Integrated Social Sciences, B.S.",
        "campuses": [
            "World Campus"
        ]
    },
    {
        "program": "Integrative Arts, B.A. (Abington)",
        "campuses": [
            "Abington"
        ]
    },
    {
        "program": "Integrative Arts, B.A. (Arts and Architecture)",
        "campuses": [
            "University Park"
        ]
    },
    {
        "program": "Integrative Science, B.S. (Abington)",
        "campuses": [
            "Abington"
        ]
    },
    {
        "program": "Integrative Science, B.S. (Berks)",
        "campuses": [
            "Berks"
        ]
    },
    {
        "program": "Integrative Science, B.S. (Capital)",
        "campuses": [
            "Harrisburg"
        ]
    },
    {
        "program": "Integrative Science, B.S. (Science)",
        "campuses": [
            "University Park"
        ]
    },
    {
        "program": "Integrative Science, B.S. (University College)",
        "campuses": [
            "Scranton",
            "York"
        ]
    },
    {
        "program": "Interdisciplinary Business with Engineering Studies, B.S. (Behrend)",
        "campuses": [
            "Erie"
        ]
    },
    {
        "program": "Interdisciplinary Business with Engineering Studies, B.S. (Berks)",
        "campuses": [
            "Berks"
        ]
    },
    {
        "program": "Interdisciplinary Science and Business, B.S.",
        "campuses": [
            "Erie"
        ]
    },
    {
        "program": "International Business, B.S.",
        "campuses": [
            "Erie"
        ]
    },
    {
        "program": "International Politics, B.A.",
        "campuses": [
            "University Park",
            "World Campus"
        ]
    },
    {
        "program": "Italian, B.A.",
        "campuses": [
            "University Park"
        ]
    },
    {
        "program": "Italian, B.S.",
        "campuses": [
            "University Park"
        ]
    },
    {
        "program": "Japanese, B.A.",
        "campuses": [
            "University Park"
        ]
    },
    {
        "program": "Jewish Studies, B.A.",
        "campuses": [
            "University Park"
        ]
    },
    {
        "program": "Journalism, B.A.",
        "campuses": [
            "University Park"
        ]
    },
    {
        "program": "Kinesiology, B.S. (Altoona)",
        "campuses": [
            "Altoona"
        ]
    },
    {
        "program": "Kinesiology, B.S. (Berks)",
        "campuses": [
            "Berks"
        ]
    },
    {
        "program": "Kinesiology, B.S. (Capital)",
        "campuses": [
            "Harrisburg"
        ]
    },
    {
        "program": "Kinesiology, B.S. (Health and Human Development)",
        "campuses": [
            "University Park"
        ]
    },
    {
        "program": "Korean, B.A.",
        "campuses": [
            "University Park"
        ]
    },
    {
        "program": "Labor and Human Resources, B.A.",
        "campuses": [
            "University Park",
            "World Campus"
        ]
    },
    {
        "program": "Labor and Human Resources, B.S.",
        "campuses": [
            "University Park",
            "World Campus"
        ]
    },
    {
        "program": "Landscape Architecture, B.L.A.",
        "campuses": [
            "University Park"
        ]
    },
    {
        "program": "Landscape Contracting, B.S.",
        "campuses": [
            "University Park"
        ]
    },
    {
        "program": "Latin American Studies, B.A.",
        "campuses": [
            "University Park"
        ]
    },
    {
        "program": "Law and Society, B.A.",
        "campuses": [
            "World Campus"
        ]
    },
    {
        "program": "Linguistics, B.A.",
        "campuses": [
            "University Park"
        ]
    },
    {
        "program": "Management Information Systems, B.S. (Behrend)",
        "campuses": [
            "Erie"
        ]
    },
    {
        "program": "Management, B.S. (Business)",
        "campuses": [
            "University Park"
        ]
    },
    {
        "program": "Management, B.S. (Capital)",
        "campuses": [
            "Harrisburg"
        ]
    },
    {
        "program": "Marketing, B.S. (Behrend)",
        "campuses": [
            "Erie"
        ]
    },
    {
        "program": "Marketing, B.S. (Business)",
        "campuses": [
            "University Park"
        ]
    },
    {
        "program": "Marketing, B.S. (Capital)",
        "campuses": [
            "Harrisburg",
            "World Campus"
        ]
    },
    {
        "program": "Materials Science and Engineering, B.S.",
        "campuses": [
            "University Park"
        ]
    },
    {
        "program": "Mathematical Sciences, B.S.",
        "campuses": [
            "Harrisburg"
        ]
    },
    {
        "program": "Mathematics, B.A.",
        "campuses": [
            "University Park"
        ]
    },
    {
        "program": "Mathematics, B.S. (Behrend)",
        "campuses": [
            "Erie"
        ]
    },
    {
        "program": "Mathematics, B.S. (Science)",
        "campuses": [
            "University Park"
        ]
    },
    {
        "program": "Mechanical Engineering Technology, B.S. (Behrend)",
        "campuses": [
            "Erie"
        ]
    },
    {
        "program": "Mechanical Engineering Technology, B.S. (Capital)",
        "campuses": [
            "Harrisburg"
        ]
    },
    {
        "program": "Mechanical Engineering, B.S. (Altoona)",
        "campuses": [
            "Altoona"
        ]
    },
    {
        "program": "Mechanical Engineering, B.S. (Behrend)",
        "campuses": [
            "Erie"
        ]
    },
    {
        "program": "Mechanical Engineering, B.S. (Berks)",
        "campuses": [
            "Berks"
        ]
    },
    {
        "program": "Mechanical Engineering, B.S. (Capital)",
        "campuses": [
            "Harrisburg"
        ]
    },
    {
        "program": "Mechanical Engineering, B.S. (Engineering)",
        "campuses": [
            "Scranton",
            "University Park"
        ]
    },
    {
        "program": "Media and Communication, B.A.",
        "campuses": [
            "Erie"
        ]
    },
    {
        "program": "Media Studies, B.A.",
        "campuses": [
            "University Park"
        ]
    },
    {
        "program": "Medieval Studies, B.A.",
        "campuses": [
            "University Park"
        ]
    },
    {
        "program": "Meteorology and Atmospheric Science, B.S.",
        "campuses": [
            "University Park"
        ]
    },
    {
        "program": "Microbiology, B.S.",
        "campuses": [
            "University Park"
        ]
    },
    {
        "program": "Middle East Studies, B.A.",
        "campuses": [
            "University Park"
        ]
    },
    {
        "program": "Middle Level Education, B.S.",
        "campuses": [
            "University Park"
        ]
    },
    {
        "program": "Mining Engineering, B.S.",
        "campuses": [
            "University Park"
        ]
    },
    {
        "program": "Multidisciplinary Arts, Social Sciences, Sciences, and Humanities, B.A.",
        "campuses": [
            "Erie"
        ]
    },
    {
        "program": "Multidisciplinary Studies, B.A. (Abington)",
        "campuses": [
            "Abington"
        ]
    },
    {
        "program": "Multidisciplinary Studies, B.A. (Altoona)",
        "campuses": [
            "Altoona"
        ]
    },
    {
        "program": "Multidisciplinary Studies, B.A. (Liberal Arts)",
        "campuses": [
            "University Park",
            "World Campus"
        ]
    },
    {
        "program": "Multidisciplinary Studies, B.A. (University College)",
        "campuses": [
            "Brandywine",
            "DuBois",
            "Greater Allegheny",
            "Hazleton",
            "Mont Alto",
            "Scranton",
            "Shenango"
        ]
    },
    {
        "program": "Music Education, B.M.E.",
        "campuses": [
            "University Park"
        ]
    },
    {
        "program": "Music Technology, B.M.",
        "campuses": [
            "University Park"
        ]
    },
    {
        "program": "Music, B.A.",
        "campuses": [
            "University Park"
        ]
    },
    {
        "program": "Music, B.M.",
        "campuses": [
            "University Park"
        ]
    },
    {
        "program": "Musical Arts, B.M.A.",
        "campuses": [
            "University Park"
        ]
    },
    {
        "program": "Musical Theatre, B.F.A.",
        "campuses": [
            "University Park"
        ]
    },
    {
        "program": "Naval Science/Naval Reserve Officer Training Corps (NROTC)",
        "campuses": []
    },
    {
        "program": "Neurobiology, B.S.",
        "campuses": [
            "University Park"
        ]
    },
    {
        "program": "Nuclear Engineering, B.S.",
        "campuses": [
            "University Park"
        ]
    },
    {
        "program": "Nursing, B.S.N.",
        "campuses": [
            "Abington",
            "Altoona",
            "Erie",
            "Fayette",
            "Harrisburg",
            "Mont Alto",
            "Schuylkill",
            "Scranton",
            "Shenango",
            "University Park",
            "World Campus"
        ]
    },
    {
        "program": "Nutritional Sciences, B.S.",
        "campuses": [
            "University Park"
        ]
    },
    {
        "program": "Occupational Science, B.S.",
        "campuses": [
            "Mont Alto"
        ]
    },
    {
        "program": "Organizational and Professional Communication, B.A.",
        "campuses": [
            "World Campus"
        ]
    },
    {
        "program": "Organizational and Professional Communication, B.S.",
        "campuses": [
            "World Campus"
        ]
    },
    {
        "program": "Organizational Leadership, B.A.",
        "campuses": [
            "University Park",
            "World Campus"
        ]
    },
    {
        "program": "Organizational Leadership, B.S.",
        "campuses": [
            "Berks",
            "University Park",
            "World Campus"
        ]
    },
    {
        "program": "Petroleum and Natural Gas Engineering, B.S.",
        "campuses": [
            "University Park"
        ]
    },
    {
        "program": "Pharmacology and Toxicology, B.S.",
        "campuses": [
            "University Park"
        ]
    },
    {
        "program": "Philosophy, B.A.",
        "campuses": [
            "University Park"
        ]
    },
    {
        "program": "Philosophy, B.S.",
        "campuses": [
            "University Park"
        ]
    },
    {
        "program": "Physics, B.S. (Behrend)",
        "campuses": [
            "Erie"
        ]
    },
    {
        "program": "Physics, B.S. (Science)",
        "campuses": [
            "University Park"
        ]
    },
    {
        "program": "Planetary Science and Astronomy, B.S.",
        "campuses": [
            "University Park"
        ]
    },
    {
        "program": "Plant Sciences, B.S.",
        "campuses": [
            "University Park"
        ]
    },
    {
        "program": "Plastics Engineering Technology, B.S.",
        "campuses": [
            "Erie"
        ]
    },
    {
        "program": "Political Science, B.A. (Behrend)",
        "campuses": [
            "Erie"
        ]
    },
    {
        "program": "Political Science, B.A. (Capital)",
        "campuses": [
            "Harrisburg"
        ]
    },
    {
        "program": "Political Science, B.A. (Liberal Arts)",
        "campuses": []
    }
]